swarms_spm/__init__.py
swarms_spm/tests/__init__.py
swarms_spm/tests/test_system_prompt_manager.py
swarms_spm-1.0.2.dist-info/licenses/LICENSE
swarms_spm-1.0.2.dist-info/METADATA
swarms_spm-1.0.2.dist-info/WHEEL
swarms_spm-1.0.2.dist-info/top_level.txt
swarms_spm-1.0.2.dist-info/RECORD
