Metadata-Version: 2.4
Name: swarms-spm
Version: 1.0.2
Summary: A lightweight, standalone library for managing hierarchical system prompts with support for global, primary, secondary, and numbered prompts
Home-page: https://github.com/yourusername/spm
Author: ESRD_Division
License-Expression: MIT
Project-URL: Homepage, https://github.com/IlumCI/
Project-URL: Documentation, https://github.com/IlumCI/swarms-spm#readme
Project-URL: Repository, https://github.com/IlumCI/swarms-spm
Project-URL: Issues, https://github.com/IlumCI/swarms-spm/issues
Keywords: ai,agent,prompt,system-prompt,prompt-management,hierarchical-prompts,llm,swarms,multi-agent,ai-framework
Classifier: Development Status :: 4 - Beta
Classifier: Intended Audience :: Developers
Classifier: Topic :: Scientific/Engineering :: Artificial Intelligence
Classifier: Topic :: Software Development :: Libraries :: Python Modules
Classifier: Programming Language :: Python :: 3
Classifier: Programming Language :: Python :: 3.8
Classifier: Programming Language :: Python :: 3.9
Classifier: Programming Language :: Python :: 3.10
Classifier: Programming Language :: Python :: 3.11
Classifier: Programming Language :: Python :: 3.12
Requires-Python: >=3.8
License-File: LICENSE
Provides-Extra: dev
Requires-Dist: pytest>=7.0.0; extra == "dev"
Requires-Dist: pytest-cov>=4.0.0; extra == "dev"
Requires-Dist: black>=23.0.0; extra == "dev"
Requires-Dist: ruff>=0.1.0; extra == "dev"
Requires-Dist: mypy>=1.0.0; extra == "dev"
Dynamic: home-page
Dynamic: license-file
Dynamic: requires-python
